google/cloud/vision/__init__.py
google/cloud/vision/gapic_version.py
google/cloud/vision/py.typed
google/cloud/vision_helpers/__init__.py
google/cloud/vision_helpers/decorators.py
google/cloud/vision_v1/__init__.py
google/cloud/vision_v1/gapic_metadata.json
google/cloud/vision_v1/gapic_version.py
google/cloud/vision_v1/py.typed
google/cloud/vision_v1/services/__init__.py
google/cloud/vision_v1/services/image_annotator/__init__.py
google/cloud/vision_v1/services/image_annotator/async_client.py
google/cloud/vision_v1/services/image_annotator/client.py
google/cloud/vision_v1/services/image_annotator/transports/__init__.py
google/cloud/vision_v1/services/image_annotator/transports/base.py
google/cloud/vision_v1/services/image_annotator/transports/grpc.py
google/cloud/vision_v1/services/image_annotator/transports/grpc_asyncio.py
google/cloud/vision_v1/services/image_annotator/transports/rest.py
google/cloud/vision_v1/services/image_annotator/transports/rest_base.py
google/cloud/vision_v1/services/product_search/__init__.py
google/cloud/vision_v1/services/product_search/async_client.py
google/cloud/vision_v1/services/product_search/client.py
google/cloud/vision_v1/services/product_search/pagers.py
google/cloud/vision_v1/services/product_search/transports/__init__.py
google/cloud/vision_v1/services/product_search/transports/base.py
google/cloud/vision_v1/services/product_search/transports/grpc.py
google/cloud/vision_v1/services/product_search/transports/grpc_asyncio.py
google/cloud/vision_v1/services/product_search/transports/rest.py
google/cloud/vision_v1/services/product_search/transports/rest_base.py
google/cloud/vision_v1/types/__init__.py
google/cloud/vision_v1/types/geometry.py
google/cloud/vision_v1/types/image_annotator.py
google/cloud/vision_v1/types/product_search.py
google/cloud/vision_v1/types/product_search_service.py
google/cloud/vision_v1/types/text_annotation.py
google/cloud/vision_v1/types/web_detection.py
google/cloud/vision_v1p1beta1/__init__.py
google_cloud_vision-3.10.1.dist-info/LICENSE
google_cloud_vision-3.10.1.dist-info/METADATA
google_cloud_vision-3.10.1.dist-info/WHEEL
google_cloud_vision-3.10.1.dist-info/top_level.txt
google_cloud_vision-3.10.1.dist-info/RECORD
